main.py
dzt-0.0.1.dist-info/METADATA
dzt-0.0.1.dist-info/WHEEL
dzt-0.0.1.dist-info/top_level.txt
dzt-0.0.1.dist-info/RECORD
